Metadata-Version: 2.1
Name: cdatastructs
Version: 0.2.0
Summary: Simple data structures accessible from both Python and C.
Home-page: UNKNOWN
Author: Jan Seifert
Author-email: jan.seifert@fotkyzcest.net
License: BSD
Platform: UNKNOWN
Classifier: Development Status :: 3 - Alpha
Classifier: License :: OSI Approved :: BSD License
Classifier: Programming Language :: Python :: 3.4
Classifier: Programming Language :: Python :: 3.5
Classifier: Programming Language :: Python :: 3.6
Classifier: Programming Language :: Python :: 3.7
